README.rst
setup.py
nphelper/__init__.py
nphelper/nphelper.py
nphelper.egg-info/PKG-INFO
nphelper.egg-info/SOURCES.txt
nphelper.egg-info/dependency_links.txt
nphelper.egg-info/requires.txt
nphelper.egg-info/top_level.txt
test/test_block.py
test/test_cartesian.py
test/test_multi_dot.py