Metadata-Version: 1.1
Name: nphelper
Version: 0.0.5
Summary: nphelper - convenient numpy helper functions
Home-page: https://github.com/sotte/nphelper
Author: Stefan Otte
Author-email: stefan.otte@gmail.com
License: MIT
Download-URL: https://github.com/sotte/nphelper
Platform: UNKNOWN
